{
    "locations": [
        {
            "name": "Minas Tirith - House of Healing",
            "url": "_o7gHiAIYkA",
            "location": [
                1328,
                5290
            ]
        },
        {
            "name": "Hobbiton",
            "url": "BjPOXC-1Zxk",
            "location": [
                3907,
                2431
            ]
        },
        {
            "name": "Argonath",
            "url": "DngL9FJUztI",
            "location": [
                2006.710938,
                4979.78125
            ]
        },
        {
            "name": "Bree (Night)",
            "url": "7a6nbSgH7rk",
            "location": [
                3937,
                2901
            ]
        },
        {
            "name": "The Prancing Pony",
            "url": "ym0LnYzu3jY",
            "location": [
                3915,
                2933
            ]
        },
        {
            "name": "Celondim",
            "url": "hvs-qqnIxuU",
            "location": [
                4196,
                1778
            ]
        },
        {
            "name": "Rain in the Trollshaws",
            "url": "mOJgKDPa5Ac",
            "location": [
                4259,
                4019
            ]
        },
        {
            "name": "Evendim",
            "url": "eC4AzyL-3jQ",
            "location": [
                4363,
                2349
            ]
        },
        {
            "name": "Bree (Day)",
            "url": "XIYtTE3-L-M",
            "location": [
                3886,
                2907
            ]
        },
        {
            "name": "Thorin's Hall",
            "url": "nSb2JSYb6Ng",
            "location": [
                3886,
                2907
            ]
        },
        {
            "name": "Tom Bombadil's House",
            "url": "KwxwwNtiWc4",
            "location": [
                3670,
                3194
            ]
        },
        {
            "name": "Storm in the Shire",
            "url": "2NmmzfkM2no",
            "location": [
                3740,
                2452
            ]
        },
        {
            "name": "Lothlórien (Night)",
            "url": "HSm7fcWrBfs",
            "location": [
                3173,
                4445
            ]
        },
        {
            "name": "Dol Amroth",
            "url": "ci0s2F7tSyc",
            "location": [
                935,
                4048
            ]
        },
        {
            "name": "Last Homely House",
            "url": "YVllYhdDjxE",
            "location": [
                4044,
                4208
            ]
        },
        {
            "name": "Blackroot Vale",
            "url": "GftvKVWNoUU",
            "location": [
                1575,
                4248
            ]
        },
        {
            "name": "Amon Raith",
            "url": "aPKWrVwNRMA",
            "location": [
                4178,
                2941
            ]
        },
        {
            "name": "Inside Tom Bombadil's House",
            "url": "QHfJp385LHg",
            "location": [
                3654,
                3157
            ]
        },
        {
            "name": "Galadriel's Garden",
            "url": "M-C8jqwTUhk",
            "location": [
                2993.5,
                4527.5
            ]
        },
        {
            "name": "Cape of Belfalas Music (Sunset)",
            "url": "yHP-OdhmwUw",
            "location": [
                564,
                4282
            ]
        },
        {
            "name": "Western Gondor",
            "url": "KAdO7JgbchU",
            "location": [
                1376,
                3348
            ]
        },
        {
            "name": "Lake-Town",
            "url": "MdoKubHbTKI",
            "location": [
                4330,
                5658
            ]
        },
        {
            "name": "Erebor",
            "url": "14NQO35mpPo",
            "location": [
                4558,
                5638
            ]
        },
        {
            "name": "Moria",
            "url": "Or2QHt7BEgI",
            "location": [
                3466,
                4170
            ]
        },
        {
            "name": "Rohan",
            "url": "LUO5qhpD2pA",
            "location": [
                2146,
                4362
            ]
        },
        {
            "name": "Mt. Doom",
            "url": "E6bVF4hM5iM",
            "location": [
                1458,
                5940
            ]
        },
        {
            "name": "Misty Mountains",
            "url": "BSFbKIW8HGs",
            "location": [
                2938,
                4000
            ]
        },
        {
            "name": "Isengard",
            "url": "jVFCSMf4ECs",
            "location": [
                2240,
                3816
            ]
        },
        {
            "name": "Fangorn",
            "url": "QVYwqQVcB8U",
            "location": [
                2542,
                4264
            ]
        },
        {
            "name": "Dol Goldur",
            "url": "bT_xLoZL7pg",
            "location": [
                3100,
                5016
            ]
        },
        {
            "name": "Forochel",
            "url": "3Ku3vXuo_uc",
            "location": [
                5224,
                2174
            ]
        },
        {
            "name": "Woodland Realm",
            "url": "nzNQLEmGlTE",
            "location": [
                4402,
                5470
            ]
        },
        {
            "name": "Beorn's Halls",
            "url": "nzNQLEmGlTE",
            "location": [
                4402,
                5470
            ]
        },
        {
            "name": "The Shire (Night)",
            "url": "V98phlSNOxE",
            "location": [
                4002,
                2418
            ]
        },
        {
            "name": "Rhun",
            "url": "Fb_0LlAMMKk",
            "location": [
                2680,
                7448
            ]
        },
        {
            "name": "Iron Hills",
            "url": "UbKC1rjUNG8",
            "location": [
                4512,
                6520
            ]
        },
        {
            "name": "The Angle",
            "url": "2DG3hbbqxpo",
            "location": [
                3624,
                3720
            ]
        },
        {
            "name": "Mirkwood",
            "url": "o5jICXSLgGs",
            "location": [
                3736,
                5248
            ]
        },
        {
            "name": "Enedwaith",
            "url": "NcplkI2Z8Po",
            "location": [
                2552,
                2928
            ]
        },
        {
            "name": "Dunland",
            "url": "KOuluEaad80",
            "location": [
                2780,
                3664
            ]
        },
        {
            "name": "Goblin Town",
            "url": "eq6trjRkYKI",
            "location": [
                4222,
                4500
            ]
        },
        {
            "name": "Ered Luin",
            "url": "68V3_AMhUK8",
            "location": [
                4584,
                1376
            ]
        },
        {
            "name": "Angmar",
            "url": "JtF61Ko9_08",
            "location": [
                5032,
                3696
            ]
        },
        {
            "name": "The Wold",
            "url": "lcera0ZbVpY",
            "location": [
                2424,
                4680
            ]
        },
        {
            "name": "Anorien",
            "url": "_131rsjY0Io",
            "location": [
                1568,
                5488
            ]
        },
        {
            "name": "Harad",
            "url": "vM0SkePnTGY",
            "location": [
                376, 5260
            ]
        }
    ]
}
